ax3_email/__init__.py
ax3_email/apps.py
ax3_email/backends.py
ax3_email/settings.py
ax3_email/tasks.py
ax3_email/utils.py
ax3_email-2.0.0.dist-info/LICENSE
ax3_email-2.0.0.dist-info/METADATA
ax3_email-2.0.0.dist-info/WHEEL
ax3_email-2.0.0.dist-info/top_level.txt
ax3_email-2.0.0.dist-info/RECORD
