Metadata-Version: 2.1
Name: ax3-email
Version: 2.0.0
Summary: AX3 Email is a Django application designed to send emails using Huey tasks.
Author-email: Felipe Gonzalez <felipe.gonzalez@axiacore.com>
Requires-Python: >=3.10
License-File: LICENSE
Requires-Dist: django >=5.0.0
Requires-Dist: huey >=2.4.5
Requires-Dist: premailer >=2.5.1
